melvil_booklist/__init__.py
melvil_booklist/book/__init__.py
melvil_booklist/book/book.py
melvil_booklist/booklist/__init__.py
melvil_booklist/booklist/booklist.py
melvil_booklist/helper/__init__.py
melvil_booklist/helper/helper.py
melvil_booklist/melvil_booklist.py
melvil_booklist/reading/__init__.py
melvil_booklist/reading/reading.py
melvil_booklist/search/__init__.py
melvil_booklist/search/search.py
melvil_booklist/setup.py
melvil_booklist-1.0.4.dist-info/entry_points.txt
melvil_booklist-1.0.4.dist-info/LICENSE.txt
melvil_booklist-1.0.4.dist-info/WHEEL
melvil_booklist-1.0.4.dist-info/METADATA
melvil_booklist-1.0.4.dist-info/RECORD
