Metadata-Version: 2.1
Name: melvil-booklist
Version: 1.0.4
Summary: A command line book management tool.
Author: Sean
Author-email: sean14520@gmail.com
Requires-Python: >=3.8,<4.0
Classifier: Programming Language :: Python :: 3
Classifier: Programming Language :: Python :: 3.8
Classifier: Programming Language :: Python :: 3.9
Classifier: Programming Language :: Python :: 3.10
Requires-Dist: bs4 (>=0.0.1,<0.0.2)
Requires-Dist: inquirer (>=2.10.0,<3.0.0)
Requires-Dist: python-Levenshtein (>=0.12.2,<0.13.0)
Requires-Dist: regex (>=2022.8.17,<2023.0.0)
Requires-Dist: requests (>=2.28.1,<3.0.0)
Requires-Dist: thefuzz (>=0.19.0,<0.20.0)
Requires-Dist: tqdm (>=4.64.0,<5.0.0)
Requires-Dist: typer[all] (>=0.6.1,<0.7.0)
